ZetcodeSymfonyJiaochengChuyiFix1/README.md
ZetcodeSymfonyJiaochengChuyiFix1/__init__.py
ZetcodeSymfonyJiaochengChuyiFix1/__main__.py
ZetcodeSymfonyJiaochengChuyiFix1/file.epub
ZetcodeSymfonyJiaochengChuyiFix1/index.html
ZetcodeSymfonyJiaochengChuyiFix1/css/__init__.py
ZetcodeSymfonyJiaochengChuyiFix1/css/annotations.css
ZetcodeSymfonyJiaochengChuyiFix1/css/main.css
ZetcodeSymfonyJiaochengChuyiFix1/css/normalize.css
ZetcodeSymfonyJiaochengChuyiFix1/css/popup.css
ZetcodeSymfonyJiaochengChuyiFix1/font/__init__.py
ZetcodeSymfonyJiaochengChuyiFix1/font/fontello.eot
ZetcodeSymfonyJiaochengChuyiFix1/font/fontello.svg
ZetcodeSymfonyJiaochengChuyiFix1/font/fontello.ttf
ZetcodeSymfonyJiaochengChuyiFix1/font/fontello.woff
ZetcodeSymfonyJiaochengChuyiFix1/img/__init__.py
ZetcodeSymfonyJiaochengChuyiFix1/img/annotator-glyph-sprite.png
ZetcodeSymfonyJiaochengChuyiFix1/img/annotator-icon-sprite.png
ZetcodeSymfonyJiaochengChuyiFix1/img/apple-touch-icon.png
ZetcodeSymfonyJiaochengChuyiFix1/img/cancelfullscreen.png
ZetcodeSymfonyJiaochengChuyiFix1/img/close.png
ZetcodeSymfonyJiaochengChuyiFix1/img/fullscreen.png
ZetcodeSymfonyJiaochengChuyiFix1/img/loader.gif
ZetcodeSymfonyJiaochengChuyiFix1/img/menu-icon.png
ZetcodeSymfonyJiaochengChuyiFix1/img/save.png
ZetcodeSymfonyJiaochengChuyiFix1/img/saved.png
ZetcodeSymfonyJiaochengChuyiFix1/img/settings-s.png
ZetcodeSymfonyJiaochengChuyiFix1/img/settings.png
ZetcodeSymfonyJiaochengChuyiFix1/img/star.png
ZetcodeSymfonyJiaochengChuyiFix1/js/__init__.py
ZetcodeSymfonyJiaochengChuyiFix1/js/epub.js
ZetcodeSymfonyJiaochengChuyiFix1/js/epub.min.js
ZetcodeSymfonyJiaochengChuyiFix1/js/epub.min.map
ZetcodeSymfonyJiaochengChuyiFix1/js/hooks.min.js
ZetcodeSymfonyJiaochengChuyiFix1/js/hooks.min.map
ZetcodeSymfonyJiaochengChuyiFix1/js/reader.js
ZetcodeSymfonyJiaochengChuyiFix1/js/reader.js.map
ZetcodeSymfonyJiaochengChuyiFix1/js/reader.min.js
ZetcodeSymfonyJiaochengChuyiFix1/js/reader.min.map
ZetcodeSymfonyJiaochengChuyiFix1/js/hooks/__init__.py
zetcode_symfony_jiaocheng_chuyi_fix1-2025.3.24.1.dist-info/METADATA
zetcode_symfony_jiaocheng_chuyi_fix1-2025.3.24.1.dist-info/WHEEL
zetcode_symfony_jiaocheng_chuyi_fix1-2025.3.24.1.dist-info/entry_points.txt
zetcode_symfony_jiaocheng_chuyi_fix1-2025.3.24.1.dist-info/top_level.txt
zetcode_symfony_jiaocheng_chuyi_fix1-2025.3.24.1.dist-info/RECORD
